specky/__about__.py
specky/__init__.py
specky/_main.py
specky/cli/__init__.py
specky/cli/check.py
specky/cli/show.py
specky-0.1.5.dist-info/LICENSE
specky-0.1.5.dist-info/METADATA
specky-0.1.5.dist-info/WHEEL
specky-0.1.5.dist-info/entry_points.txt
specky-0.1.5.dist-info/top_level.txt
specky-0.1.5.dist-info/RECORD
