Metadata-Version: 2.1
Name: specky
Version: 0.1.5
Summary: Audio file spectral analysis
Home-page: https://github.com/nschloe/specky
Author: Nico Schlömer
Author-email: nico.schloemer@gmail.com
License: GPL-3.0-or-later
Project-URL: Code, https://github.com/nschloe/specky
Project-URL: Issues, https://github.com/nschloe/specky/issues
Project-URL: Funding, https://github.com/sponsors/nschloe
Platform: UNKNOWN
Classifier: Development Status :: 4 - Beta
Classifier: Intended Audience :: Science/Research
Classifier: License :: OSI Approved :: MIT License
Classifier: Operating System :: OS Independent
Classifier: Programming Language :: Python :: 3
Classifier: Programming Language :: Python :: 3.6
Classifier: Programming Language :: Python :: 3.7
Classifier: Programming Language :: Python :: 3.8
Classifier: Programming Language :: Python :: 3.9
Classifier: Topic :: Scientific/Engineering
Classifier: Topic :: Utilities
Requires-Python: >=3.6
Requires-Dist: colorama
Requires-Dist: matplotlib
Requires-Dist: mutagen
Requires-Dist: numpy
Requires-Dist: pydub
Requires-Dist: scipy
Requires-Dist: importlib-metadata ; python_version < "3.8"
Provides-Extra: all
Requires-Dist: matplotlib ; extra == 'all'
Provides-Extra: png
Requires-Dist: matplotlib ; extra == 'png'
